{
    "flake-registry": {
        "cargoLocks": null,
        "date": "2024-06-03",
        "extract": null,
        "name": "flake-registry",
        "passthru": null,
        "pinned": false,
        "src": {
            "deepClone": false,
            "fetchSubmodules": false,
            "leaveDotGit": false,
            "name": null,
            "owner": "nixos",
            "repo": "flake-registry",
            "rev": "895a65f8d5acf848136ee8fe8e8f736f0d27df96",
            "sha256": "sha256-HKvoLGZUsBpjkxWkdtctGYj6RH0bl6vcw0OjTOqyzJk=",
            "type": "github"
        },
        "version": "895a65f8d5acf848136ee8fe8e8f736f0d27df96"
    },
    "harper-ls": {
        "cargoLocks": null,
        "date": null,
        "extract": null,
        "name": "harper-ls",
        "passthru": null,
        "pinned": false,
        "src": {
            "deepClone": false,
            "fetchSubmodules": false,
            "leaveDotGit": false,
            "name": null,
            "owner": "elijah-potter",
            "repo": "harper",
            "rev": "v0.9.3",
            "sha256": "sha256-HwyBmjc8kpBpwPQC2zkykn8wv+7v1Q5NMg+Ohz3XeD8=",
            "type": "github"
        },
        "version": "v0.9.3"
    },
    "hyprland-workspaces": {
        "cargoLocks": null,
        "date": null,
        "extract": null,
        "name": "hyprland-workspaces",
        "passthru": null,
        "pinned": false,
        "src": {
            "deepClone": false,
            "fetchSubmodules": false,
            "leaveDotGit": false,
            "name": null,
            "owner": "FieldofClay",
            "repo": "hyprland-workspaces",
            "rev": "v2.0.1",
            "sha256": "sha256-GhUjvFMlgjTdgtV9ASW7IqE2dBktPyOlRwg6qM1r7vc=",
            "type": "github"
        },
        "version": "v2.0.1"
    },
    "joker": {
        "cargoLocks": null,
        "date": null,
        "extract": null,
        "name": "joker",
        "passthru": null,
        "pinned": false,
        "src": {
            "deepClone": false,
            "fetchSubmodules": false,
            "leaveDotGit": false,
            "name": null,
            "owner": "candid82",
            "repo": "joker",
            "rev": "v1.4.0",
            "sha256": "sha256-Y7FaW3V80mXp3l87srTLyhF45MlNH7QUZ5hrTudPtDU=",
            "type": "github"
        },
        "version": "v1.4.0"
    },
    "kamp": {
        "cargoLocks": null,
        "date": null,
        "extract": null,
        "name": "kamp",
        "passthru": null,
        "pinned": false,
        "src": {
            "deepClone": false,
            "fetchSubmodules": false,
            "leaveDotGit": false,
            "name": null,
            "owner": "kyleisah",
            "repo": "Klipper-Adaptive-Meshing-Purging",
            "rev": "v1.1.2",
            "sha256": "sha256-anBGjLtYlyrxeNVy1TEMcAGTVUFrGClLuoJZuo3xlDM=",
            "type": "github"
        },
        "version": "v1.1.2"
    },
    "kibana": {
        "cargoLocks": null,
        "date": null,
        "extract": null,
        "name": "kibana",
        "passthru": null,
        "pinned": false,
        "src": {
            "arch": null,
            "finalImageName": null,
            "finalImageTag": null,
            "imageDigest": "sha256:35caffeb480e6cd55afaad72f78820f802e21c2d73996c1b46c2998c0513f977",
            "imageName": "library/kibana",
            "imageTag": "7.17.23",
            "os": null,
            "sha256": "sha256-mXYN+rQI8kgtjirtJQbvGxjdauQKITJaD1ivoQk05kI=",
            "tlsVerify": null
        },
        "version": "7.17.23"
    },
    "linux-rockchip": {
        "cargoLocks": null,
        "date": "2024-07-10",
        "extract": null,
        "name": "linux-rockchip",
        "passthru": null,
        "pinned": false,
        "src": {
            "deepClone": false,
            "fetchSubmodules": false,
            "leaveDotGit": false,
            "name": null,
            "owner": "armbian",
            "repo": "linux-rockchip",
            "rev": "709c51c64e1652d4f8c87b1815db86f56d188268",
            "sha256": "sha256-YZdWNhLopRyaEBojqMLMYEMKV6V0HcFgFmDbRSbBhRo=",
            "type": "github"
        },
        "version": "709c51c64e1652d4f8c87b1815db86f56d188268"
    },
    "sf-mono-nerd-font": {
        "cargoLocks": null,
        "date": null,
        "extract": null,
        "name": "sf-mono-nerd-font",
        "passthru": null,
        "pinned": false,
        "src": {
            "deepClone": false,
            "fetchSubmodules": false,
            "leaveDotGit": false,
            "name": null,
            "owner": "epk",
            "repo": "SF-Mono-Nerd-Font",
            "rev": "v18.0d1e1.0",
            "sha256": "sha256-f5A/vTKCUxdMhCqv0/ikF46tRrx5yZfIkvfExb3/XEQ=",
            "type": "github"
        },
        "version": "v18.0d1e1.0"
    },
    "tfautomv": {
        "cargoLocks": null,
        "date": null,
        "extract": null,
        "name": "tfautomv",
        "passthru": null,
        "pinned": false,
        "src": {
            "deepClone": false,
            "fetchSubmodules": false,
            "leaveDotGit": false,
            "name": null,
            "owner": "busser",
            "repo": "tfautomv",
            "rev": "v0.6.2",
            "sha256": "sha256-qUeIbHJqxGkt2esMm4w6fM52ZE16jWnxugVXxqBh1Qc=",
            "type": "github"
        },
        "version": "v0.6.2"
    }
}